gaussian_splatting_mcmc/train.py
gaussian_splatting_mcmc/train_reduced.py
gaussian_splatting_mcmc/trainer/__init__.py
gaussian_splatting_mcmc/trainer/combinations.py
gaussian_splatting_mcmc/trainer/noise.py
gaussian_splatting_mcmc/trainer/relocate.py
gaussian_splatting_mcmc/trainer/scale_opacity_reg.py
gaussian_splatting_mcmc/trainer/diff_gaussian_rasterization/_C.cp312-win_amd64.pyd
gaussian_splatting_mcmc/trainer/diff_gaussian_rasterization/__init__.py
gaussian_splatting_mcmc-1.1.2.dist-info/licenses/LICENSE.md
gaussian_splatting_mcmc-1.1.2.dist-info/METADATA
gaussian_splatting_mcmc-1.1.2.dist-info/WHEEL
gaussian_splatting_mcmc-1.1.2.dist-info/top_level.txt
gaussian_splatting_mcmc-1.1.2.dist-info/RECORD
