Metadata-Version: 2.4
Name: gaussian_splatting_mcmc
Version: 1.1.2
Summary: Refactored python training code for 3D Gaussian Splatting as Markov Chain Monte Carlo
Home-page: https://github.com/yindaheng98/3dgs-mcmc
Author: yindaheng98
Author-email: yindaheng98@gmail.com
Classifier: Programming Language :: Python :: 3
License-File: LICENSE.md
Requires-Dist: gaussian-splatting
Dynamic: author
Dynamic: author-email
Dynamic: classifier
Dynamic: description
Dynamic: description-content-type
Dynamic: home-page
Dynamic: license-file
Dynamic: requires-dist
Dynamic: summary
